Metadata-Version: 1.1
Name: pdf-writer
Version: 0.1
Summary: Python library to write text on top of PDF
Home-page: https://github.com/shridarpatil/pdf_writer
Author: Shridhar Patil
Author-email: shridharpatil2792@gmail.com
License: UNKNOWN
Download-URL: https://github.com/shridarpatil/pdf_writer/archive/0.1.tar.gz
Keywords: pdf writer,Pdf Editor
Platform: UNKNOWN
